[
    {
        "name": "All-In (Zerg)",
        "chest_unopened_img": "/images/items/close.png",
        "chest_opened_img": "/images/items/open.png",
        "overlay_background": "#000000",
        "access_rules": [
            " "
        ],
        "sections": [
            {
                "name": "Victory",
                "access_rules": [],
                "visibility_rules": [],
                "item_count": 1
            },
            {
                "name": "First Kerrigan Attack",
                "access_rules": [],
                "visibility_rules": [],
                "item_count": 1
            },
            {
                "name": "Second Kerrigan Attack",
                "access_rules": [],
                "visibility_rules": [],
                "item_count": 1
            },
            {
                "name": "Third Kerrigan Attack",
                "access_rules": [],
                "visibility_rules": [],
                "item_count": 1
            },
            {
                "name": "Fourth Kerrigan Attack",
                "access_rules": [],
                "visibility_rules": [],
                "item_count": 1
            },
            {
                "name": "Fifth Kerrigan Attack",
                "access_rules": [],
                "visibility_rules": [],
                "item_count": 1
            },
            {
                "name": "Victory Cache (1)",
                "access_rules": [],
                "visibility_rules": [],
                "item_count": 1
            },
            {
                "name": "Victory Cache (2)",
                "access_rules": [],
                "visibility_rules": [],
                "item_count": 1
            },
            {
                "name": "Victory Cache (3)",
                "access_rules": [],
                "visibility_rules": [],
                "item_count": 1
            },
            {
                "name": "Victory Cache (4)",
                "access_rules": [],
                "visibility_rules": [],
                "item_count": 1
            },
            {
                "name": "Victory Cache (5)",
                "access_rules": [],
                "visibility_rules": [],
                "item_count": 1
            },
            {
                "name": "Victory Cache (6)",
                "access_rules": [],
                "visibility_rules": [],
                "item_count": 1
            },
            {
                "name": "Victory Cache (7)",
                "access_rules": [],
                "visibility_rules": [],
                "item_count": 1
            },
            {
                "name": "Victory Cache (8)",
                "access_rules": [],
                "visibility_rules": [],
                "item_count": 1
            },
            {
                "name": "Victory Cache (9)",
                "access_rules": [],
                "visibility_rules": [],
                "item_count": 1
            },
            {
                "name": "Victory Cache (10)",
                "access_rules": [],
                "visibility_rules": [],
                "item_count": 1
            }
        ],
        "map_locations": [
            {
                "map": "All-In (Zerg)",
                "x": 863,
                "y": 2056,
                "size": 6
            }
        ]
    }
]